pysswords/__init__.py
pysswords/__main__.py
pysswords/cli.py
pysswords/crypt.py
pysswords/python_two.py
pysswords/utils.py
pysswords/db/__init__.py
pysswords/db/credential.py
pysswords/db/database.py
pysswords/db/parsers.py
pysswords-0.0.12.dist-info/DESCRIPTION.rst
pysswords-0.0.12.dist-info/entry_points.txt
pysswords-0.0.12.dist-info/METADATA
pysswords-0.0.12.dist-info/metadata.json
pysswords-0.0.12.dist-info/RECORD
pysswords-0.0.12.dist-info/top_level.txt
pysswords-0.0.12.dist-info/WHEEL
tests/__init__.py
tests/test.py
