Metadata-Version: 2.0
Name: pysswords
Version: 0.0.12
Summary: Manage your login credentials from the terminal painlessly.
Home-page: https://github.com/marcwebbie/pysswords
Author: Marcwebbie
Author-email: marcwebbie@gmail.com
License: License :: OSI Approved :: MIT License
Download-URL: https://pypi.python.org/pypi/pysswords
Platform: UNKNOWN
Classifier: Development Status :: 2 - Pre-Alpha
Classifier: Environment :: Console
Classifier: Intended Audience :: End Users/Desktop
Classifier: Natural Language :: English
Classifier: Operating System :: OS Independent
Classifier: Topic :: Security :: Cryptography
Classifier: License :: OSI Approved :: MIT License
Classifier: Programming Language :: Python
Classifier: Programming Language :: Python :: 2.7
Classifier: Programming Language :: Python :: 3
Classifier: Programming Language :: Python :: 3.2
Classifier: Programming Language :: Python :: 3.3
Classifier: Programming Language :: Python :: 3.4
Requires-Dist: gnupg (==1.4.0)
Requires-Dist: pyperclip (==1.5.7)
Requires-Dist: tabulate (==0.7.3)
Requires-Dist: colorama (==0.3.2)
Requires-Dist: PyYAML (==3.11)
